[
    {
        "studentId": 1,
        "firstName": "Aashish",
        "middleName": "",
        "lastName": "Rimal",
        "gender": "male",
        "dateOfBirth": "2055-05-03T00:00:00.000Z",
        "phoneNo": 9854781269,
        "email": "Aashish727@gmail.com",
        "address": "Lamachaur",
        "classId": 2,
        "rollNo": 1
    },
    {
        "studentId": 2,
        "firstName": "Abhishek",
        "lastName": "Bhandari",
        "middleName": "",
        "gender": "male",
        "dateOfBirth": "2058-11-24T00:00:00.000Z",
        "phoneNo": 9847515527,
        "email": "Abhishek795@gmail.com",
        "address": "Kushma",
        "classId": 2,
        "rollNo": 2
    },
    {
        "studentId": 3,
        "firstName": "Agesh",
        "middleName": "Bahadur",
        "lastName": "Thapa",
        "gender": "male",
        "dateOfBirth": "2057-12-19T00:00:00.000Z",
        "phoneNo": 9833418960,
        "email": "Agesh753@gmail.com",
        "address": "Kushma",
        "classId": 5,
        "rollNo": 3
    },
    {
        "studentId": 4,
        "firstName": "Ajay",
        "middleName": "",
        "lastName": "Chaudary",
        "gender": "male",
        "dateOfBirth": "2054-12-10T00:00:00.000Z",
        "phoneNo": 9850837113,
        "email": "Ajay625@gmail.com",
        "address": "Chitwan",
        "classId": 2,
        "rollNo": 4
    },
    {
        "studentId": 5,
        "firstName": "Anjan",
        "middleName": "",
        "lastName": "Poudel",
        "gender": "male",
        "dateOfBirth": "2054-03-25T00:00:00.000Z",
        "phoneNo": 9826757929,
        "email": "Anjan178@gmail.com",
        "address": "Lamjung",
        "classId": 2,
        "rollNo": 5
    },
    {
        "studentId": 6,
        "firstName": "Anup",
        "middleName": "",
        "lastName": "Adhikari",
        "gender": "male",
        "dateOfBirth": "2057-09-19T00:00:00.000Z",
        "phoneNo": 9827937354,
        "email": "Anup738@gmail.com",
        "address": "Lamachaur",
        "classId": 5,
        "rollNo": 6
    },
    {
        "studentId": 7,
        "firstName": "Anup",
        "middleName": "",
        "lastName": "Giri",
        "gender": "male",
        "dateOfBirth": "2055-09-07T00:00:00.000Z",
        "phoneNo": 9890991276,
        "email": "Anup465@gmail.com",
        "address": "Kushma",
        "classId": 5,
        "rollNo": 7
    },
    {
        "studentId": 8,
        "firstName": "Ashok",
        "middleName": "",
        "lastName": "Budhathoki",
        "gender": "male",
        "dateOfBirth": "2056-02-15T00:00:00.000Z",
        "phoneNo": 9855205216,
        "email": "Ashok541@gmail.com",
        "address": "Lamachaur",
        "classId": 5,
        "rollNo": 8
    },
    {
        "studentId": 9,
        "firstName": "Bibek",
        "middleName": "",
        "lastName": "Chalise",
        "gender": "male",
        "dateOfBirth": "2055-10-25T00:00:00.000Z",
        "phoneNo": 9837293583,
        "email": "Bibek455@gmail.com",
        "address": "Gaidakot",
        "classId": 2,
        "rollNo": 9
    },
    {
        "studentId": 10,
        "firstName": "Bibek",
        "middleName": "",
        "lastName": "Lamichhane",
        "gender": "male",
        "dateOfBirth": "2058-06-11T00:00:00.000Z",
        "phoneNo": 9889562361,
        "email": "Bibek848@gmail.com",
        "address": "Lamjung",
        "classId": 4,
        "rollNo": 10
    },
    {
        "studentId": 11,
        "firstName": "Bidhya",
        "middleName": "",
        "lastName": "Poudel",
        "gender": "female",
        "dateOfBirth": "2055-07-24T00:00:00.000Z",
        "phoneNo": 9826648745,
        "email": "Bidhya521@gmail.com",
        "address": "Butwal",
        "classId": 4,
        "rollNo": 11
    },
    {
        "studentId": 12,
        "firstName": "Bishal",
        "middleName": "",
        "lastName": "Poudel",
        "gender": "male",
        "dateOfBirth": "2054-06-13T00:00:00.000Z",
        "phoneNo": 9815644456,
        "email": "Bishal711@gmail.com",
        "address": "Argakhanchi",
        "classId": 2,
        "rollNo": 12
    },
    {
        "studentId": 13,
        "firstName": "Bishal",
        "middleName": "",
        "lastName": "Shrestha",
        "gender": "male",
        "dateOfBirth": "2056-12-10T00:00:00.000Z",
        "phoneNo": 9868769988,
        "email": "Bishal440@gmail.com",
        "address": "Kushma",
        "classId": 2,
        "rollNo": 13
    },
    {
        "studentId": 14,
        "firstName": "Daya",
        "middleName": "Raj",
        "lastName": "Dhungana",
        "gender": "male",
        "dateOfBirth": "2056-07-14T00:00:00.000Z",
        "phoneNo": 9845634287,
        "email": "Daya727@gmail.com",
        "address": "Palpa",
        "classId": 2,
        "rollNo": 14
    },
    {
        "studentId": 15,
        "firstName": "Dhurba",
        "middleName": "",
        "lastName": "Sharma",
        "gender": "male",
        "dateOfBirth": "2054-03-29T00:00:00.000Z",
        "phoneNo": 9859958377,
        "email": "Dhurba361@gmail.com",
        "address": "Kushma",
        "classId": 4,
        "rollNo": 15
    },
    {
        "studentId": 16,
        "firstName": "Dhudu",
        "middleName": "Ram",
        "lastName": "Thapa",
        "gender": "male",
        "dateOfBirth": "2056-10-19T00:00:00.000Z",
        "phoneNo": 9886961138,
        "email": "Dhudu608@gmail.com",
        "address": "Lamachaur",
        "classId": 2,
        "rollNo": 16
    },
    {
        "studentId": 17,
        "firstName": "Dhurba",
        "middleName": "",
        "lastName": "Baral",
        "gender": "male",
        "dateOfBirth": "2057-05-18T00:00:00.000Z",
        "phoneNo": 9856454457,
        "email": "Dhurba119@gmail.com",
        "address": "Butwal",
        "classId": 1,
        "rollNo": 17
    },
    {
        "studentId": 18,
        "firstName": "Dipendra",
        "middleName": "",
        "lastName": "Neupane",
        "gender": "male",
        "dateOfBirth": "2054-02-03T00:00:00.000Z",
        "phoneNo": 9846101017,
        "email": "Dipendra883@gmail.com",
        "address": "Lamjung",
        "classId": 3,
        "rollNo": 18
    },
    {
        "studentId": 19,
        "firstName": "Eldrin",
        "middleName": "",
        "lastName": "Gurung",
        "gender": "male",
        "dateOfBirth": "2057-05-14T00:00:00.000Z",
        "phoneNo": 9892126891,
        "email": "Eldrin116@gmail.com",
        "address": "Chitwan",
        "classId": 3,
        "rollNo": 19
    },
    {
        "studentId": 20,
        "firstName": "Ichchha",
        "middleName": "Babu",
        "lastName": "Bhattrai",
        "gender": "male",
        "dateOfBirth": "2055-01-29T00:00:00.000Z",
        "phoneNo": 9830314716,
        "email": "Ichchha273@gmail.com",
        "address": "Lamachaur",
        "classId": 3,
        "rollNo": 20
    },
    {
        "studentId": 21,
        "firstName": "Kushal",
        "middleName": "",
        "lastName": "Pangeni",
        "gender": "male",
        "dateOfBirth": "2055-12-08T00:00:00.000Z",
        "phoneNo": 9807981693,
        "email": "Kushal225@gmail.com",
        "address": "Lamachaur",
        "classId": 1,
        "rollNo": 21
    },
    {
        "studentId": 22,
        "firstName": "Mishan",
        "middleName": "",
        "lastName": "Khatri",
        "gender": "male",
        "dateOfBirth": "2058-02-09T00:00:00.000Z",
        "phoneNo": 9838820205,
        "email": "Mishan442@gmail.com",
        "address": "Kathmandu",
        "classId": 2,
        "rollNo": 22
    },
    {
        "studentId": 23,
        "firstName": "Nabin",
        "middleName": "",
        "lastName": "Shrestha",
        "gender": "male",
        "dateOfBirth": "2055-01-31T00:00:00.000Z",
        "phoneNo": 9875364036,
        "email": "Nabin267@gmail.com",
        "address": "Chitwan",
        "classId": 3,
        "rollNo": 23
    },
    {
        "studentId": 24,
        "firstName": "Nitesh",
        "middleName": "",
        "lastName": "Pokhrel",
        "gender": "male",
        "dateOfBirth": "2058-07-20T00:00:00.000Z",
        "phoneNo": 9869544640,
        "email": "Nitesh369@gmail.com",
        "address": "Butwal",
        "classId": 4,
        "rollNo": 24
    },
    {
        "studentId": 25,
        "firstName": "Om",
        "middleName": "",
        "lastName": "Sharma",
        "gender": "male",
        "dateOfBirth": "2057-07-19T00:00:00.000Z",
        "phoneNo": 9816422435,
        "email": "Om689@gmail.com",
        "address": "Lamjung",
        "classId": 3,
        "rollNo": 25
    },
    {
        "studentId": 26,
        "firstName": "Om",
        "middleName": "Prakash",
        "lastName": "Tharu",
        "gender": "male",
        "dateOfBirth": "2054-11-27T00:00:00.000Z",
        "phoneNo": 9838469083,
        "email": "Om470@gmail.com",
        "address": "Butwal",
        "classId": 1,
        "rollNo": 26
    },
    {
        "studentId": 27,
        "firstName": "Pallavi",
        "middleName": "",
        "lastName": "Pandey",
        "gender": "female",
        "dateOfBirth": "2056-02-03T00:00:00.000Z",
        "phoneNo": 9831499918,
        "email": "Pallavi182@gmail.com",
        "address": "Butwal",
        "classId": 4,
        "rollNo": 27
    },
    {
        "studentId": 28,
        "firstName": "Paras",
        "middleName": "",
        "lastName": "Panta",
        "gender": "male",
        "dateOfBirth": "2055-01-22T00:00:00.000Z",
        "phoneNo": 9880848674,
        "email": "Paras344@gmail.com",
        "address": "Lamjung",
        "classId": 4,
        "rollNo": 28
    },
    {
        "studentId": 29,
        "firstName": "Prabin",
        "middleName": "",
        "lastName": "Gautam",
        "gender": "male",
        "dateOfBirth": "2058-01-03T00:00:00.000Z",
        "phoneNo": 9872091244,
        "email": "Prabin863@gmail.com",
        "address": "Lamjung",
        "classId": 3,
        "rollNo": 29
    },
    {
        "studentId": 30,
        "firstName": "Prajwal",
        "middleName": "",
        "lastName": "Chaudhary",
        "gender": "male",
        "dateOfBirth": "2058-05-13T00:00:00.000Z",
        "phoneNo": 9868207754,
        "email": "Prajwal803@gmail.com",
        "address": "Kathmandu",
        "classId": 4,
        "rollNo": 30
    },
    {
        "studentId": 31,
        "firstName": "Prashamsha",
        "middleName": "",
        "lastName": "Poudel",
        "gender": "female",
        "dateOfBirth": "2057-03-31T00:00:00.000Z",
        "phoneNo": 9839102192,
        "email": "Prashamsha584@gmail.com",
        "address": "Pokhara",
        "classId": 5,
        "rollNo": 31
    },
    {
        "studentId": 32,
        "firstName": "Prashant",
        "middleName": "",
        "lastName": "Panta",
        "gender": "male",
        "dateOfBirth": "2058-10-01T00:00:00.000Z",
        "phoneNo": 9833025717,
        "email": "Prashant408@gmail.com",
        "address": "Chitwan",
        "classId": 4,
        "rollNo": 32
    },
    {
        "studentId": 33,
        "firstName": "Rajan",
        "middleName": "",
        "lastName": "Devkota",
        "gender": "male",
        "dateOfBirth": "2054-03-02T00:00:00.000Z",
        "phoneNo": 9806653989,
        "email": "Rajan380@gmail.com",
        "address": "Tanahue",
        "classId": 3,
        "rollNo": 33
    },
    {
        "studentId": 34,
        "firstName": "Rasmi",
        "middleName": "",
        "lastName": "Bhattrai",
        "gender": "female",
        "dateOfBirth": "2057-10-06T00:00:00.000Z",
        "phoneNo": 9856407158,
        "email": "Rasmi333@gmail.com",
        "address": "Kathmandu",
        "classId": 1,
        "rollNo": 34
    },
    {
        "studentId": 35,
        "firstName": "Roshan",
        "middleName": "",
        "lastName": "KC",
        "gender": "male",
        "dateOfBirth": "2054-05-10T00:00:00.000Z",
        "phoneNo": 9842588252,
        "email": "Roshan438@gmail.com",
        "address": "Kushma",
        "classId": 2,
        "rollNo": 35
    },
    {
        "studentId": 36,
        "firstName": "Roshan",
        "middleName": "",
        "lastName": "Thapa",
        "gender": "male",
        "dateOfBirth": "2058-07-28T00:00:00.000Z",
        "phoneNo": 9865546599,
        "email": "Roshan626@gmail.com",
        "address": "Lamjung",
        "classId": 1,
        "rollNo": 36
    },
    {
        "studentId": 37,
        "firstName": "Roshan",
        "middleName": "",
        "lastName": "Thapa",
        "gender": "male",
        "dateOfBirth": "2056-02-16T00:00:00.000Z",
        "phoneNo": 9826691042,
        "email": "Roshan529@gmail.com",
        "address": "Illam",
        "classId": 2,
        "rollNo": 37
    },
    {
        "studentId": 38,
        "firstName": "Sagar",
        "middleName": "",
        "lastName": "Khanal",
        "gender": "male",
        "dateOfBirth": "2058-12-26T00:00:00.000Z",
        "phoneNo": 9899639022,
        "email": "Sagar444@gmail.com",
        "address": "Lamjung",
        "classId": 3,
        "rollNo": 38
    },
    {
        "studentId": 39,
        "firstName": "Sagar",
        "middleName": "",
        "lastName": "Subedi",
        "gender": "male",
        "dateOfBirth": "2055-03-15T00:00:00.000Z",
        "phoneNo": 9865805226,
        "email": "Sagar150@gmail.com",
        "address": "Lamachaur",
        "classId": 1,
        "rollNo": 39
    },
    {
        "studentId": 40,
        "firstName": "Samikshya",
        "middleName": "",
        "lastName": "Paudel",
        "gender": "female",
        "dateOfBirth": "2055-05-14T00:00:00.000Z",
        "phoneNo": 9847382536,
        "email": "Samikshya210@gmail.com",
        "address": "Pokhara",
        "classId": 5,
        "rollNo": 40
    },
    {
        "studentId": 41,
        "firstName": "Santosh",
        "middleName": "",
        "lastName": "Basnet",
        "gender": "male",
        "dateOfBirth": "2055-12-14T00:00:00.000Z",
        "phoneNo": 9892296981,
        "email": "Santosh571@gmail.com",
        "address": "Kathmandu",
        "classId": 5,
        "rollNo": 41
    },
    {
        "studentId": 42,
        "firstName": "Santwana",
        "middleName": "",
        "lastName": "Parajuli",
        "gender": "female",
        "dateOfBirth": "2056-05-19T00:00:00.000Z",
        "phoneNo": 9803833957,
        "email": "Santwana495@gmail.com",
        "address": "Kushma",
        "classId": 4,
        "rollNo": 42
    },
    {
        "studentId": 43,
        "firstName": "Saugat",
        "middleName": "",
        "lastName": "Paudel",
        "gender": "male",
        "dateOfBirth": "2057-06-07T00:00:00.000Z",
        "phoneNo": 9857434398,
        "email": "Saugat801@gmail.com",
        "address": "Butwal",
        "classId": 5,
        "rollNo": 43
    },
    {
        "studentId": 44,
        "firstName": "Shushil",
        "middleName": "",
        "lastName": "Paudel",
        "gender": "male",
        "dateOfBirth": "2055-07-11T00:00:00.000Z",
        "phoneNo": 9814778252,
        "email": "Shushil343@gmail.com",
        "address": "Kathmandu",
        "classId": 1,
        "rollNo": 44
    },
    {
        "studentId": 45,
        "firstName": "Siddhant",
        "middleName": "",
        "lastName": "Shrestha",
        "gender": "male",
        "dateOfBirth": "2058-12-27T00:00:00.000Z",
        "phoneNo": 9871045057,
        "email": "Siddhant239@gmail.com",
        "address": "Pokhara",
        "classId": 3,
        "rollNo": 45
    },
    {
        "studentId": 46,
        "firstName": "Sudhir",
        "middleName": "",
        "lastName": "Paudel",
        "gender": "male",
        "dateOfBirth": "2055-12-01T00:00:00.000Z",
        "phoneNo": 9851467570,
        "email": "Sudhir491@gmail.com",
        "address": "Kathmandu",
        "classId": 1,
        "rollNo": 46
    },
    {
        "studentId": 47,
        "firstName": "Sulabh",
        "middleName": "",
        "lastName": "Ghimire",
        "gender": "male",
        "dateOfBirth": "2056-12-06T00:00:00.000Z",
        "phoneNo": 9848062130,
        "email": "Sulabh631@gmail.com",
        "address": "Pokhara",
        "classId": 4,
        "rollNo": 47
    },
    {
        "studentId": 48,
        "firstName": "Suresh",
        "middleName": "",
        "lastName": "Pantha",
        "gender": "male",
        "dateOfBirth": "2057-02-19T00:00:00.000Z",
        "phoneNo": 9890194637,
        "email": "Suresh540@gmail.com",
        "address": "Damauli",
        "classId": 3,
        "rollNo": 48
    }
]
